ppmml/__init__.py
ppmml/base_converter.py
ppmml/converter.py
ppmml/evaluator.py
ppmml/lightgbm.py
ppmml/r.py
ppmml/sklearn.py
ppmml/spark.py
ppmml/tensorflow.py
ppmml/utils.py
ppmml/xgboost.py
ppmml/resources/__init__.py
ppmml/tests/__init__.py
ppmml/tests/lightgbm_test.py
ppmml/tests/r_test.py
ppmml/tests/sklearn_test.py
ppmml/tests/spark_test.py
ppmml/tests/tensorflow_test.py
ppmml/tests/xgboost_test.py
ppmml-0.0.1.dist-info/METADATA
ppmml-0.0.1.dist-info/RECORD
ppmml-0.0.1.dist-info/WHEEL
ppmml-0.0.1.dist-info/top_level.txt
